ultraimport.cpython-311-i386-linux-gnu.so
ultraimport/__init__.py
ultraimport/setup.py
ultraimport/ultraimport.py
ultraimport-0.1.0.dist-info/METADATA
ultraimport-0.1.0.dist-info/WHEEL
ultraimport-0.1.0.dist-info/top_level.txt
ultraimport-0.1.0.dist-info/RECORD
