Metadata-Version: 2.4
Name: ultraimport
Version: 0.1.0
Summary: Get control over your imports -- no matter how you run your code.
License:                                  Apache License
Project-URL: Homepage, https://github.com/ronny-rentner/ultraimport
Project-URL: Repository, https://github.com/ronny-rentner/ultraimport
Project-URL: Documentation, https://github.com/ronny-rentner/ultraimport/tree/main/docs
Requires-Python: >=3.9
